{
"navigation":[
    {
        "Home":"http://mysite/home.com",
        "Contact":"http://mysite/comtact.com",
        "About Us":"http:mystie/about.com",
        "Services":"http://mystie/services.com"
    },
    {
        "Home Sample1":"http://mysite/home/catalog",
        "Home Sample2":"http://mysite/home/sample2",
        "Home Sample3":"http:mystie/home/sample3",
        "Home Sample4":"http:/mystie/home/sample4"
    },
    {
        "Contact Sample1":"http://mysite/Contact/Sample1",
        "Contact Sample2":"http://mysite/contact/sample2",
        "Contact Sample3":"http://mystie/contact/sample3",
        "Contact Sample4":"http://mystie/contact/sample4"
    },
    {
        "AboutUs Sample1":"http://mysite/about/Sample1",
        "AboutUs Sample2":"http://mysite/about/sample2",
        "AboutUs Sample3":"http://mystie/about/sample3",
        "AboutUs Sample4":"http://mystie/about/sample4"
    },
    {
        "Services Sample1":"http://mysite/services/Sample1",
        "Services Sample2":"http://mysite/services/sample2",
        "Services Sample3":"http://mystie/services/sample3",
        "Services Sample4":"http://mystie/services/sample4"
    }
]    
}

